{
  "repo_name": "ZPE-FT",
  "repo_role": "secondary_product_candidate",
  "status": "PRIVATE_STAGE",
  "plain_english_summary": "Deterministic financial time-series compression, replay, and query surface for bounded market-data workflows.",
  "commercial_wedge": "Search financial patterns on compressed delayed-feed archives with deterministic replay, retained public benchmark evidence, and bounded replay fidelity. Real-market minute-bar and tick figures are bounded proxy artifacts; the open-access enterprise benchmark remains blocked on missing inputs.",
  "technical_wedge": "Deterministic financial codec with native search and replay. The retained repo artifacts show public benchmark compression plus bounded replay fidelity; Phase 06 remains blocked on missing inputs.",
  "ideal_first_buyer": "Market-data infrastructure team or quant research platform",
  "deployment_model": "SDK — Python package with optional Rust native helper",
  "proof_anchors": [
    "proofs/artifacts/public_benchmarks/phase3_public_benchmarks.json",
    "proofs/reruns/2026-03-19_alpaca_demo_smoke/ft_reconstruction_fidelity.json",
    "proofs/artifacts/real_market_benchmarks/BOUNDARY.json",
    "proofs/reruns/2026-03-21_phase06_contract_freeze_attempt_v3/missing_inputs_packet.json",
    "proofs/phase06_inputs/series_gap_matrix.csv"
  ],
  "not_claimed": [
    "Public release readiness (Phase 06 BLOCKED_MISSING_INPUTS)",
    "Broad incumbent displacement",
    "Full contract freeze",
    "Lossless volume reconstruction",
    "Universal financial data coverage",
    "Runtime coupling to ZPE-IMC"
  ],
  "family_position": "Secondary product candidate in the Zer0pa deterministic encoding family. Not the lead commercial front door.",
  "license": "LicenseRef-Zer0pa-SAL-7.0",
  "contact": "architects@zer0pa.ai"
}
